routeros_check/__init__.py
routeros_check/__main__.py
routeros_check/_scm_version.py
routeros_check/cli.py
routeros_check/context.py
routeros_check/exeption.py
routeros_check/helper.py
routeros_check/resource.py
routeros_check/check/__init__.py
routeros_check/check/interface.py
routeros_check/check/interface_gre.py
routeros_check/check/interface_vrrp.py
routeros_check/check/routing_bgp_peer.py
routeros_check/check/routing_ospf_neighbor.py
routeros_check/check/system_clock.py
routeros_check/check/system_cpu.py
routeros_check/check/system_disk.py
routeros_check/check/system_fan.py
routeros_check/check/system_license.py
routeros_check/check/system_memory.py
routeros_check/check/system_ntp_client.py
routeros_check/check/system_power.py
routeros_check/check/system_psu.py
routeros_check/check/system_temperature.py
routeros_check/check/system_update.py
routeros_check/check/system_uptime.py
routeros_check/check/tool_ping.py
routeros_check-0.11.1.dist-info/licenses/LICENSE.md
routeros_check-0.11.1.dist-info/METADATA
routeros_check-0.11.1.dist-info/WHEEL
routeros_check-0.11.1.dist-info/entry_points.txt
routeros_check-0.11.1.dist-info/top_level.txt
routeros_check-0.11.1.dist-info/RECORD
