Metadata-Version: 2.4
Name: routeros-check
Version: 0.11.1
Summary: Monitoring plugin for MikroTik devices for Icinga-Nagios-... 
Author: DinoTools
License: ### GNU GENERAL PUBLIC LICENSE
Project-URL: Homepage, https://github.com/DinoTools/monitoring-check_routeros
Keywords: RouterOS,MikroTik,Icinga,Nagios,Monitoring
Classifier: Development Status :: 5 - Production/Stable
Classifier: License :: OSI Approved :: GNU General Public License v3 or later (GPLv3+)
Classifier: Programming Language :: Python
Classifier: Programming Language :: Python :: 3
Requires-Python: >=3.8
License-File: LICENSE.md
Requires-Dist: Click
Requires-Dist: librouteros
Requires-Dist: nagiosplugin
Dynamic: license-file
